README.md
setup.cfg
setup.py
ajao_distributions/Binomialdistribution.py
ajao_distributions/Gaussiandistribution.py
ajao_distributions/Generaldistribution.py
ajao_distributions/__init__.py
ajao_distributions.egg-info/PKG-INFO
ajao_distributions.egg-info/SOURCES.txt
ajao_distributions.egg-info/dependency_links.txt
ajao_distributions.egg-info/not-zip-safe
ajao_distributions.egg-info/top_level.txt